{
  ".DS_Store": {
    "mt": "Sun Sep 20 2020 13:14:30 GMT-0500 (Central Daylight Time)",
    "exists": true,
    "state": 1,
    "path": "/Users/erick/apps/artblocks-site/.DS_Store"
  },
  ".env": {
    "mt": "Fri Oct 09 2020 21:40:14 GMT-0500 (Central Daylight Time)",
    "exists": true,
    "state": 1,
    "path": "/Users/erick/apps/artblocks-site/.env"
  },
  ".gitignore": {
    "mt": "Fri Oct 09 2020 21:40:45 GMT-0500 (Central Daylight Time)",
    "exists": true,
    "state": 1,
    "path": "/Users/erick/apps/artblocks-site/.gitignore"
  },
  "README.md": {
    "mt": "Sun Oct 04 2020 15:58:01 GMT-0500 (Central Daylight Time)",
    "exists": true,
    "state": 1,
    "path": "/Users/erick/apps/artblocks-site/README.md"
  },
  "__nc_app__ab-front-end.json": {
    "mt": "Mon Oct 19 2020 00:02:49 GMT-0500 (Central Daylight Time)",
    "exists": true,
    "state": 1,
    "path": "/Users/erick/apps/artblocks-site/__nc_app__ab-front-end.json"
  },
  "build/asset-manifest.json": {
    "mt": "Thu Sep 17 2020 09:20:47 GMT-0500 (Central Daylight Time)",
    "exists": true,
    "state": 1,
    "path": "/Users/erick/apps/artblocks-site/build/asset-manifest.json"
  },
  "build/favicon.ico": {
    "mt": "Thu Sep 17 2020 09:20:32 GMT-0500 (Central Daylight Time)",
    "exists": true,
    "state": 1,
    "path": "/Users/erick/apps/artblocks-site/build/favicon.ico"
  },
  "build/index.html": {
    "mt": "Thu Sep 17 2020 09:20:47 GMT-0500 (Central Daylight Time)",
    "exists": true,
    "state": 1,
    "path": "/Users/erick/apps/artblocks-site/build/index.html"
  },
  "build/logo192.png": {
    "mt": "Thu Sep 17 2020 09:20:32 GMT-0500 (Central Daylight Time)",
    "exists": true,
    "state": 1,
    "path": "/Users/erick/apps/artblocks-site/build/logo192.png"
  },
  "build/logo512.png": {
    "mt": "Thu Sep 17 2020 09:20:32 GMT-0500 (Central Daylight Time)",
    "exists": true,
    "state": 1,
    "path": "/Users/erick/apps/artblocks-site/build/logo512.png"
  },
  "build/manifest.json": {
    "mt": "Thu Sep 17 2020 09:20:32 GMT-0500 (Central Daylight Time)",
    "exists": true,
    "state": 1,
    "path": "/Users/erick/apps/artblocks-site/build/manifest.json"
  },
  "build/precache-manifest.d04fb6c4f100805af4af7b512187dd97.js": {
    "mt": "Thu Sep 17 2020 09:20:47 GMT-0500 (Central Daylight Time)",
    "exists": true,
    "state": 1,
    "path": "/Users/erick/apps/artblocks-site/build/precache-manifest.d04fb6c4f100805af4af7b512187dd97.js"
  },
  "build/robots.txt": {
    "mt": "Thu Sep 17 2020 09:20:32 GMT-0500 (Central Daylight Time)",
    "exists": true,
    "state": 1,
    "path": "/Users/erick/apps/artblocks-site/build/robots.txt"
  },
  "build/service-worker.js": {
    "mt": "Thu Sep 17 2020 09:20:47 GMT-0500 (Central Daylight Time)",
    "exists": true,
    "state": 1,
    "path": "/Users/erick/apps/artblocks-site/build/service-worker.js"
  },
  "build/static/css/2.9c620975.chunk.css": {
    "mt": "Thu Sep 17 2020 09:20:47 GMT-0500 (Central Daylight Time)",
    "exists": true,
    "state": 1,
    "path": "/Users/erick/apps/artblocks-site/build/static/css/2.9c620975.chunk.css"
  },
  "build/static/css/2.9c620975.chunk.css.map": {
    "mt": "Thu Sep 17 2020 09:20:47 GMT-0500 (Central Daylight Time)",
    "exists": true,
    "state": 1,
    "path": "/Users/erick/apps/artblocks-site/build/static/css/2.9c620975.chunk.css.map"
  },
  "build/static/css/main.11d832ee.chunk.css": {
    "mt": "Thu Sep 17 2020 09:20:47 GMT-0500 (Central Daylight Time)",
    "exists": true,
    "state": 1,
    "path": "/Users/erick/apps/artblocks-site/build/static/css/main.11d832ee.chunk.css"
  },
  "build/static/css/main.11d832ee.chunk.css.map": {
    "mt": "Thu Sep 17 2020 09:20:47 GMT-0500 (Central Daylight Time)",
    "exists": true,
    "state": 1,
    "path": "/Users/erick/apps/artblocks-site/build/static/css/main.11d832ee.chunk.css.map"
  },
  "build/static/js/2.aa3eac4d.chunk.js": {
    "mt": "Thu Sep 17 2020 09:20:47 GMT-0500 (Central Daylight Time)",
    "exists": true,
    "state": 1,
    "path": "/Users/erick/apps/artblocks-site/build/static/js/2.aa3eac4d.chunk.js"
  },
  "build/static/js/2.aa3eac4d.chunk.js.map": {
    "mt": "Thu Sep 17 2020 09:20:47 GMT-0500 (Central Daylight Time)",
    "exists": true,
    "state": 1,
    "path": "/Users/erick/apps/artblocks-site/build/static/js/2.aa3eac4d.chunk.js.map"
  },
  "build/static/js/main.cdb6e348.chunk.js": {
    "mt": "Thu Sep 17 2020 09:20:47 GMT-0500 (Central Daylight Time)",
    "exists": true,
    "state": 1,
    "path": "/Users/erick/apps/artblocks-site/build/static/js/main.cdb6e348.chunk.js"
  },
  "build/static/js/main.cdb6e348.chunk.js.map": {
    "mt": "Thu Sep 17 2020 09:20:47 GMT-0500 (Central Daylight Time)",
    "exists": true,
    "state": 1,
    "path": "/Users/erick/apps/artblocks-site/build/static/js/main.cdb6e348.chunk.js.map"
  },
  "build/static/js/runtime~main.42ac5946.js": {
    "mt": "Thu Sep 17 2020 09:20:47 GMT-0500 (Central Daylight Time)",
    "exists": true,
    "state": 1,
    "path": "/Users/erick/apps/artblocks-site/build/static/js/runtime~main.42ac5946.js"
  },
  "build/static/js/runtime~main.42ac5946.js.map": {
    "mt": "Thu Sep 17 2020 09:20:47 GMT-0500 (Central Daylight Time)",
    "exists": true,
    "state": 1,
    "path": "/Users/erick/apps/artblocks-site/build/static/js/runtime~main.42ac5946.js.map"
  },
  "package-lock.json": {
    "mt": "Wed Oct 21 2020 23:21:19 GMT-0500 (Central Daylight Time)",
    "exists": true,
    "state": 1,
    "path": "/Users/erick/apps/artblocks-site/package-lock.json"
  },
  "package.json": {
    "mt": "Wed Oct 21 2020 23:21:19 GMT-0500 (Central Daylight Time)",
    "exists": true,
    "state": 1,
    "path": "/Users/erick/apps/artblocks-site/package.json"
  },
  "public/favicon.ico": {
    "mt": "Tue Sep 15 2020 23:14:01 GMT-0500 (Central Daylight Time)",
    "exists": true,
    "state": 1,
    "path": "/Users/erick/apps/artblocks-site/public/favicon.ico"
  },
  "public/index.html": {
    "mt": "Sat Oct 10 2020 14:01:30 GMT-0500 (Central Daylight Time)",
    "exists": true,
    "state": 1,
    "path": "/Users/erick/apps/artblocks-site/public/index.html"
  },
  "public/logo192.png": {
    "mt": "Mon Sep 07 2020 00:36:43 GMT-0500 (Central Daylight Time)",
    "exists": true,
    "state": 1,
    "path": "/Users/erick/apps/artblocks-site/public/logo192.png"
  },
  "public/logo512.png": {
    "mt": "Mon Sep 07 2020 00:36:43 GMT-0500 (Central Daylight Time)",
    "exists": true,
    "state": 1,
    "path": "/Users/erick/apps/artblocks-site/public/logo512.png"
  },
  "public/manifest.json": {
    "mt": "Mon Sep 07 2020 00:36:43 GMT-0500 (Central Daylight Time)",
    "exists": true,
    "state": 1,
    "path": "/Users/erick/apps/artblocks-site/public/manifest.json"
  },
  "public/robots.txt": {
    "mt": "Mon Sep 07 2020 00:36:43 GMT-0500 (Central Daylight Time)",
    "exists": true,
    "state": 1,
    "path": "/Users/erick/apps/artblocks-site/public/robots.txt"
  },
  "src/App.css": {
    "mt": "Mon Oct 12 2020 17:14:25 GMT-0500 (Central Daylight Time)",
    "exists": true,
    "state": 1,
    "path": "/Users/erick/apps/artblocks-site/src/App.css"
  },
  "src/App.js": {
    "mt": "Mon Oct 19 2020 00:00:00 GMT-0500 (Central Daylight Time)",
    "exists": true,
    "state": 1,
    "path": "/Users/erick/apps/artblocks-site/src/App.js"
  },
  "src/App.test.js": {
    "mt": "Mon Sep 07 2020 00:36:43 GMT-0500 (Central Daylight Time)",
    "exists": true,
    "state": 1,
    "path": "/Users/erick/apps/artblocks-site/src/App.test.js"
  },
  "src/Highlight.js": {
    "mt": "Wed Oct 21 2020 23:57:32 GMT-0500 (Central Daylight Time)",
    "exists": true,
    "state": 1,
    "path": "/Users/erick/apps/artblocks-site/src/Highlight.js"
  },
  "src/Intro.js": {
    "mt": "Tue Oct 13 2020 00:55:17 GMT-0500 (Central Daylight Time)",
    "exists": true,
    "state": 1,
    "path": "/Users/erick/apps/artblocks-site/src/Intro.js"
  },
  "src/Learn.js": {
    "mt": "Mon Oct 19 2020 00:00:13 GMT-0500 (Central Daylight Time)",
    "exists": true,
    "state": 1,
    "path": "/Users/erick/apps/artblocks-site/src/Learn.js"
  },
  "src/Nav.js": {
    "mt": "Sun Oct 18 2020 22:34:31 GMT-0500 (Central Daylight Time)",
    "exists": true,
    "state": 1,
    "path": "/Users/erick/apps/artblocks-site/src/Nav.js"
  },
  "src/NewToken.js": {
    "mt": "Wed Oct 21 2020 23:59:05 GMT-0500 (Central Daylight Time)",
    "exists": true,
    "state": 1,
    "path": "/Users/erick/apps/artblocks-site/src/NewToken.js"
  },
  "src/Project.js": {
    "mt": "Wed Oct 21 2020 23:57:51 GMT-0500 (Central Daylight Time)",
    "exists": true,
    "state": 1,
    "path": "/Users/erick/apps/artblocks-site/src/Project.js"
  },
  "src/ProjectGallery.css": {
    "mt": "Sun Sep 20 2020 17:51:58 GMT-0500 (Central Daylight Time)",
    "exists": true,
    "state": 1,
    "path": "/Users/erick/apps/artblocks-site/src/ProjectGallery.css"
  },
  "src/ProjectGallery.js": {
    "mt": "Tue Oct 13 2020 00:52:27 GMT-0500 (Central Daylight Time)",
    "exists": true,
    "state": 1,
    "path": "/Users/erick/apps/artblocks-site/src/ProjectGallery.js"
  },
  "src/ProjectThumbOld.js": {
    "mt": "Sun Oct 04 2020 17:30:03 GMT-0500 (Central Daylight Time)",
    "exists": true,
    "state": 1,
    "path": "/Users/erick/apps/artblocks-site/src/ProjectThumbOld.js"
  },
  "src/UserGallery.js": {
    "mt": "Sun Oct 18 2020 22:17:47 GMT-0500 (Central Daylight Time)",
    "exists": true,
    "state": 1,
    "path": "/Users/erick/apps/artblocks-site/src/UserGallery.js"
  },
  "src/config.js": {
    "mt": "Mon Sep 07 2020 16:19:44 GMT-0500 (Central Daylight Time)",
    "exists": true,
    "state": 1,
    "path": "/Users/erick/apps/artblocks-site/src/config.js"
  },
  "src/index.js": {
    "mt": "Mon Sep 07 2020 00:51:10 GMT-0500 (Central Daylight Time)",
    "exists": true,
    "state": 1,
    "path": "/Users/erick/apps/artblocks-site/src/index.js"
  },
  "src/logo.svg": {
    "mt": "Mon Sep 07 2020 00:36:43 GMT-0500 (Central Daylight Time)",
    "exists": true,
    "state": 1,
    "path": "/Users/erick/apps/artblocks-site/src/logo.svg"
  },
  "src/serviceWorker.js": {
    "mt": "Mon Sep 07 2020 00:36:43 GMT-0500 (Central Daylight Time)",
    "exists": true,
    "state": 1,
    "path": "/Users/erick/apps/artblocks-site/src/serviceWorker.js"
  },
  "src/setupTests.js": {
    "mt": "Mon Sep 07 2020 00:36:43 GMT-0500 (Central Daylight Time)",
    "exists": true,
    "state": 1,
    "path": "/Users/erick/apps/artblocks-site/src/setupTests.js"
  }
}